nbmetalog/__init__.py
nbmetalog/_except_return_none.py
nbmetalog/get_dataframe_full_digest.py
nbmetalog/get_dataframe_manifest.py
nbmetalog/get_dataframe_short_digest.py
nbmetalog/get_env_context.py
nbmetalog/get_git_revision.py
nbmetalog/get_hostname.py
nbmetalog/get_interpreter.py
nbmetalog/get_notebook_cell_execution_count.py
nbmetalog/get_notebook_name.py
nbmetalog/get_notebook_path.py
nbmetalog/get_package_versions.py
nbmetalog/get_session_uuid.py
nbmetalog/get_timestamp.py
nbmetalog/nbmetalog.py
nbmetalog-0.2.6.dist-info/AUTHORS.rst
nbmetalog-0.2.6.dist-info/LICENSE
nbmetalog-0.2.6.dist-info/METADATA
nbmetalog-0.2.6.dist-info/WHEEL
nbmetalog-0.2.6.dist-info/top_level.txt
nbmetalog-0.2.6.dist-info/RECORD
