Metadata-Version: 2.1
Name: nbmetalog
Version: 0.2.6
Summary: nbmetalog helps you log jupyter notebook metadata
Home-page: https://github.com/mmore500/nbmetalog
Author: Matthew Andres Moreno
Author-email: m.more500@gmail.com
License: MIT license
Keywords: nbmetalog
Platform: UNKNOWN
Classifier: Development Status :: 2 - Pre-Alpha
Classifier: Intended Audience :: Developers
Classifier: License :: OSI Approved :: MIT License
Classifier: Natural Language :: English
Classifier: Programming Language :: Python :: 3
Classifier: Programming Language :: Python :: 3.6
Classifier: Programming Language :: Python :: 3.7
Classifier: Programming Language :: Python :: 3.8
Requires-Python: >=3.6
Requires-Dist: ipynbname (>=2021.3.2)
Requires-Dist: hurry.filesize (>=0.9)
Requires-Dist: keyname (>=0.4.1)
Requires-Dist: pandas (>=1.1.2)
Requires-Dist: pyyaml (>=5.3.1)
